WEEK#2/AdderTree/adder_tree.sv
module adder_tree (P,EA,EB,dataA,dataB,clk);
parameter M = 8 , N = 16;
output logic [N-1:0] P;
input logic clk, EA, EB; 
input logic [M-1:0] dataA, dataB;

logic [M-1:0] A, B; 
logic [N-1:0] multiplier; 
logic [3:0]  count;      // log2(15) = 3.9 ~= 4

always_ff @(posedge clk) begin
if (EA) A <= dataA;
if (EB) B <= dataB;
end
always_ff @(posedge clk) begin
if (EA || EB) begin
multiplier <= 0;
count <= 0;
end
else if (count < M) begin
if (B[count])
multiplier <= multiplier + (A << count);
count <= count + 1;
end
end
always_ff @(posedge clk) begin
if (count == M)
P <= multiplier;
end

endmodule

WEEK#2/AdderTree/tb_adder_tree.sv
`timescale 1ns/1ps

module tb_adder_tree;

parameter M = 8, N = 16;

logic clk;
logic EA, EB;
logic [M-1:0] dataA, dataB;
logic [N-1:0] P;

logic [M-1:0] A_tb, B_tb;
logic [N-1:0] expected;

integer pass_count = 0;
integer fail_count = 0;
integer i;
integer m = 4;

initial clk = 0;
always #5 clk = ~clk;

adder_tree #(M,N) dut (.P(P),.EA(EA),.EB(EB),.dataA(dataA),.dataB(dataB),.clk(clk));

initial begin
  $dumpfile("adder_tree.vcd");   // VCD file name
  $dumpvars(0, tb_adder_tree);   // top module name
end


initial begin
EA = 0; EB = 0; dataA = 0; dataB = 0; A_tb = 0; B_tb = 0; #10;

for (i = 0; i < 10; i = i + 1) begin
dataA = $urandom_range(0, 255);
dataB = $urandom_range(0, 255);

EA = 1; EB = 1;
@(posedge clk);
EA = 0; EB = 0;

A_tb = dataA; B_tb = dataB;

repeat (m) @(posedge clk); //repeat (2) @(posedge clk); //miss se poochna hai

expected = A_tb * B_tb;

if (P === expected) begin
pass_count++;
$display("TEST %0d PASS : %0d * %0d = %0d", i, A_tb, B_tb, P);
end
else begin
fail_count++;
$error("TEST %0d FAIL : %0d * %0d = %0d (expected %0d)", i, A_tb, B_tb, P, expected);
end

#5;  
end

// Summary 
$display("\n------------------ SUMMARY ------------------");
$display("Total Tests  : %0d", pass_count + fail_count);
$display("Tests Passed : %0d", pass_count);
$display("Tests Failed : %0d", fail_count);
if (fail_count == 0)
$display("OVERALL STATUS : ALL TESTS PASSED");
else
$display("OVERALL STATUS : SOME TESTS FAILED");
$display("---------------------------------------------");

$finish;
end

endmodule

WEEK#2/AdderTree/adder_tree.vcd
$date
	Tue Dec 30 15:19:43 2025
$end
$version
	Icarus Verilog
$end
$timescale
	1ps
$end
$scope module tb_adder_tree $end
$var wire 16 ! P [15:0] $end
$var reg 8 " A_tb [7:0] $end
$var reg 8 # B_tb [7:0] $end
$var reg 1 $ EA $end
$var reg 1 % EB $end
$var reg 1 & clk $end
$var reg 8 ' dataA [7:0] $end
$var reg 8 ( dataB [7:0] $end
$var reg 16 ) expected [15:0] $end
$var integer 32 * fail_count [31:0] $end
$var integer 32 + i [31:0] $end
$var integer 32 , m [31:0] $end
$var integer 32 - pass_count [31:0] $end
$scope module dut $end
$var wire 1 $ EA $end
$var wire 1 % EB $end
$var wire 1 & clk $end
$var wire 8 . dataA [7:0] $end
$var wire 8 / dataB [7:0] $end
$var reg 8 0 A [7:0] $end
$var reg 8 1 B [7:0] $end
$var reg 16 2 P [15:0] $end
$var reg 4 3 count [3:0] $end
$var reg 16 4 multiplier [15:0] $end
$upscope $end
$upscope $end
$enddefinitions $end
#0
$dumpvars
bx 4
bx 3
bx 2
bx 1
bx 0
b0 /
b0 .
b0 -
b100 ,
bx +
b0 *
bx )
b0 (
b0 '
0&
0%
0$
b0 #
b0 "
bx !
$end
#5000
1&
#10000
0&
1%
1$
b1000000 (
b1000000 /
b10010010 '
b10010010 .
b0 +
#15000
b1000000 #
b10010010 "
0%
0$
1&
#20000
0&
#25000
1&
#30000
0&
#35000
1&
#40000
0&
#45000
1&
#50000
0&
#55000
b1 *
b10010010000000 )
1&
#60000
1%
1$
b110001 (
b110001 /
b100 '
b100 .
b1 +
0&
#65000
b110001 #
b100 "
0%
0$
1&
#70000
0&
#75000
1&
#80000
0&
#85000
1&
#90000
0&
#95000
1&
#100000
0&
#105000
b10 *
b11000100 )
1&
#110000
1%
1$
b11000110 (
b11000110 /
b10000110 '
b10000110 .
b10 +
0&
#115000
b11000110 #
b10000110 "
0%
0$
1&
#120000
0&
#125000
1&
#130000
0&
#135000
1&
#140000
0&
#145000
1&
#150000
0&
#155000
b11 *
b110011110100100 )
1&
#160000
1%
1$
b1001 (
b1001 /
b110010 '
b110010 .
b11 +
0&
#165000
b1001 #
b110010 "
0%
0$
1&
#170000
0&
#175000
1&
#180000
0&
#185000
1&
#190000
0&
#195000
1&
#200000
0&
#205000
b100 *
b111000010 )
1&
#210000
1%
1$
b10000110 (
b10000110 /
b10000000 '
b10000000 .
b100 +
0&
#215000
b10000110 #
b10000000 "
0%
0$
1&
#220000
0&
#225000
1&
#230000
0&
#235000
1&
#240000
0&
#245000
1&
#250000
0&
#255000
b101 *
b100001100000000 )
1&
#260000
1%
1$
b10011110 (
b10011110 /
b10111011 '
b10111011 .
b101 +
0&
#265000
b10011110 #
b10111011 "
0%
0$
1&
#270000
0&
#275000
1&
#280000
0&
#285000
1&
#290000
0&
#295000
1&
#300000
0&
#305000
b110 *
b111001101101010 )
1&
#310000
1%
1$
b11000110 (
b11000110 /
b11110110 '
b11110110 .
b110 +
0&
#315000
b11000110 #
b11110110 "
0%
0$
1&
#320000
0&
#325000
1&
#330000
0&
#335000
1&
#340000
0&
#345000
1&
#350000
0&
#355000
b111 *
b1011111001000100 )
1&
#360000
1%
1$
b1100011 (
b1100011 /
b11111100 '
b11111100 .
b111 +
0&
#365000
b1100011 #
b11111100 "
0%
0$
1&
#370000
0&
#375000
1&
#380000
0&
#385000
1&
#390000
0&
#395000
1&
#400000
0&
#405000
b1000 *
b110000101110100 )
1&
#410000
1%
1$
b1010101 (
b1010101 /
b1100010 '
b1100010 .
b1000 +
0&
#415000
b1010101 #
b1100010 "
0%
0$
1&
#420000
0&
#425000
1&
#430000
0&
#435000
1&
#440000
0&
#445000
1&
#450000
0&
#455000
b1001 *
b10000010001010 )
1&
#460000
1%
1$
b111011 (
b111011 /
b11110010 '
b11110010 .
b1001 +
0&
#465000
b111011 #
b11110010 "
0%
0$
1&
#470000
0&
#475000
1&
#480000
0&
#485000
1&
#490000
0&
#495000
1&
#500000
0&
#505000
b1010 *
b11011111000110 )
1&
#510000
b1010 +
0&
