WEEK#1/Encoder/Encoder8_3.sv
module Encoder8_3(out, in);

input [7:0] in;
output reg [2:0] out;

always @(*) begin
if (in & 8'd1)    out = 3'd0;
else if (in & 8'd2) out = 3'd1;
else if (in & 8'd4) out = 3'd2;
else if (in & 8'd8) out = 3'd3;
else if (in & 8'd16) out = 3'd4;
else if (in & 8'd32) out = 3'd5;
else if (in & 8'd64) out = 3'd6;
else if (in & 8'd128) out = 3'd7;
else out = 3'd0;
end
endmodule

WEEK#1/Encoder/tb_Encoder8_3.sv
`timescale 1ns/1ps
module tb_Encoder8_3();
reg [7:0] in;
wire [2:0] out;

reg [2:0] expected_out;

integer i;
integer pass = 1;
integer fail = 0;

Encoder8_3 dut(.in(in), .out(out));

//GTK WAVE
initial begin
$dumpfile("Encoder8_3.vcd");
$dumpvars(0, tb_Encoder8_3);
end
    
task check;
begin
if (out === expected_out) begin
$display("PASS: in=%b => out=%b", in, out);
pass = pass + 1;
end else begin
$display("FAIL: in=%b => out=%b (expected=%b)", in, out, expected_out);
fail = fail + 1;
end
end
endtask

initial begin
$display("===== Encoder8_3 Testbench Start =====");
//DIRECT TEST
in = 8'd1;  #10; expected_out = 3'd0; check();
in = 8'd2;  #10; expected_out = 3'd1; check();
in = 8'd4;  #10; expected_out = 3'd2; check();
in = 8'd8;  #10; expected_out = 3'd3; check();
in = 8'd16; #10; expected_out = 3'd4; check();
in = 8'd32; #10; expected_out = 3'd5; check();
in = 8'd64; #10; expected_out = 3'd6; check();
in = 8'd128;#10; expected_out = 3'd7; check();

//RANDOM TEST
for (i = 0; i < 10; i = i + 1) begin
in = $urandom % 256; #10;

if (in & 8'b00000001) expected_out = 3'b000;
else if (in & 8'b00000010) expected_out = 3'b001;
else if (in & 8'b00000100) expected_out = 3'b010;
else if (in & 8'b00001000) expected_out = 3'b011;
else if (in & 8'b00010000) expected_out = 3'b100;
else if (in & 8'b00100000) expected_out = 3'b101;
else if (in & 8'b01000000) expected_out = 3'b110;
else if (in & 8'b10000000) expected_out = 3'b111;
else expected_out = 3'b000;

check();
end

in = 8'b00001000; #10; expected_out = 3'b000;

check();

// Summary
$display("-------------SUMMARY--------------");
$display("Total Passed: %0d", pass);
$display("Total Failed: %0d", fail);
$display("----------------------------------");
$finish;
end
endmodule

WEEK#1/Encoder/Encoder8_3.vcd
$date
	Tue Dec 23 14:22:30 2025
$end
$version
	Icarus Verilog
$end
$timescale
	1ps
$end
$scope module tb_Encoder8_3 $end
$var wire 3 ! out [2:0] $end
$var reg 3 " expected_out [2:0] $end
$var reg 8 # in [7:0] $end
$var integer 32 $ fail [31:0] $end
$var integer 32 % i [31:0] $end
$var integer 32 & pass [31:0] $end
$scope module dut $end
$var wire 8 ' in [7:0] $end
$var reg 3 ( out [2:0] $end
$upscope $end
$scope task check $end
$upscope $end
$upscope $end
$enddefinitions $end
#0
$dumpvars
b0 (
b1 '
b1 &
bx %
b0 $
b1 #
bx "
b0 !
$end
#10000
b1 !
b1 (
b10 #
b10 '
b10 &
b0 "
#20000
b10 !
b10 (
b100 #
b100 '
b11 &
b1 "
#30000
b11 !
b11 (
b1000 #
b1000 '
b100 &
b10 "
#40000
b100 !
b100 (
b10000 #
b10000 '
b101 &
b11 "
#50000
b101 !
b101 (
b100000 #
b100000 '
b110 &
b100 "
#60000
b110 !
b110 (
b1000000 #
b1000000 '
b111 &
b101 "
#70000
b111 !
b111 (
b10000000 #
b10000000 '
b1000 &
b110 "
#80000
b10 !
b10 (
b100100 #
b100100 '
b0 %
b1001 &
b111 "
#90000
b0 !
b0 (
b10000001 #
b10000001 '
b1 %
b1010 &
b10 "
#100000
b1001 #
b1001 '
b10 %
b1011 &
b0 "
#110000
b1100011 #
b1100011 '
b11 %
b1100 &
#120000
b1101 #
b1101 '
b100 %
b1101 &
#130000
b10001101 #
b10001101 '
b101 %
b1110 &
#140000
b1100101 #
b1100101 '
b110 %
b1111 &
#150000
b1 !
b1 (
b10010 #
b10010 '
b111 %
b10000 &
#160000
b0 !
b0 (
b1 #
b1 '
b1000 %
b10001 &
b1 "
#170000
b1101 #
b1101 '
b1001 %
b10010 &
b0 "
#180000
b11 !
b11 (
b1000 #
b1000 '
b1010 %
b10011 &
#190000
b1 $
