WEEK#1/Adder32Bit/fulladder.sv
module fulladder (sum,cout,a,b,cin);
output sum, cout;
input a,b,cin;
assign sum = a^b^cin;
assign cout = (a & b) | (a & cin)|(b & cin);
endmodule

WEEK#1/Adder32Bit/Adder32Bit.sv
module Adder32Bit(sum, cout, a, b, cin);
parameter N = 32;
output [N-1:0] sum;
output cout;
input [N-1:0] a;
input [N-1:0] b;
input cin;

wire [N-2:0] c; 

fulladder fa0  (.sum(sum[0]),  .cout(c[0]),  .a(a[0]),  .b(b[0]),  .cin(cin));
fulladder fa1  (.sum(sum[1]),  .cout(c[1]),  .a(a[1]),  .b(b[1]),  .cin(c[0]));
fulladder fa2  (.sum(sum[2]),  .cout(c[2]),  .a(a[2]),  .b(b[2]),  .cin(c[1]));
fulladder fa3  (.sum(sum[3]),  .cout(c[3]),  .a(a[3]),  .b(b[3]),  .cin(c[2]));
fulladder fa4  (.sum(sum[4]),  .cout(c[4]),  .a(a[4]),  .b(b[4]),  .cin(c[3]));
fulladder fa5  (.sum(sum[5]),  .cout(c[5]),  .a(a[5]),  .b(b[5]),  .cin(c[4]));
fulladder fa6  (.sum(sum[6]),  .cout(c[6]),  .a(a[6]),  .b(b[6]),  .cin(c[5]));
fulladder fa7  (.sum(sum[7]),  .cout(c[7]),  .a(a[7]),  .b(b[7]),  .cin(c[6]));
fulladder fa8  (.sum(sum[8]),  .cout(c[8]),  .a(a[8]),  .b(b[8]),  .cin(c[7]));
fulladder fa9  (.sum(sum[9]),  .cout(c[9]),  .a(a[9]),  .b(b[9]),  .cin(c[8]));
fulladder fa10 (.sum(sum[10]), .cout(c[10]), .a(a[10]), .b(b[10]), .cin(c[9]));
fulladder fa11 (.sum(sum[11]), .cout(c[11]), .a(a[11]), .b(b[11]), .cin(c[10]));
fulladder fa12 (.sum(sum[12]), .cout(c[12]), .a(a[12]), .b(b[12]), .cin(c[11]));
fulladder fa13 (.sum(sum[13]), .cout(c[13]), .a(a[13]), .b(b[13]), .cin(c[12]));
fulladder fa14 (.sum(sum[14]), .cout(c[14]), .a(a[14]), .b(b[14]), .cin(c[13]));
fulladder fa15 (.sum(sum[15]), .cout(c[15]), .a(a[15]), .b(b[15]), .cin(c[14]));
fulladder fa16 (.sum(sum[16]), .cout(c[16]), .a(a[16]), .b(b[16]), .cin(c[15]));
fulladder fa17 (.sum(sum[17]), .cout(c[17]), .a(a[17]), .b(b[17]), .cin(c[16]));
fulladder fa18 (.sum(sum[18]), .cout(c[18]), .a(a[18]), .b(b[18]), .cin(c[17]));
fulladder fa19 (.sum(sum[19]), .cout(c[19]), .a(a[19]), .b(b[19]), .cin(c[18]));
fulladder fa20 (.sum(sum[20]), .cout(c[20]), .a(a[20]), .b(b[20]), .cin(c[19]));
fulladder fa21 (.sum(sum[21]), .cout(c[21]), .a(a[21]), .b(b[21]), .cin(c[20]));
fulladder fa22 (.sum(sum[22]), .cout(c[22]), .a(a[22]), .b(b[22]), .cin(c[21]));
fulladder fa23 (.sum(sum[23]), .cout(c[23]), .a(a[23]), .b(b[23]), .cin(c[22]));
fulladder fa24 (.sum(sum[24]), .cout(c[24]), .a(a[24]), .b(b[24]), .cin(c[23]));
fulladder fa25 (.sum(sum[25]), .cout(c[25]), .a(a[25]), .b(b[25]), .cin(c[24]));
fulladder fa26 (.sum(sum[26]), .cout(c[26]), .a(a[26]), .b(b[26]), .cin(c[25]));
fulladder fa27 (.sum(sum[27]), .cout(c[27]), .a(a[27]), .b(b[27]), .cin(c[26]));
fulladder fa28 (.sum(sum[28]), .cout(c[28]), .a(a[28]), .b(b[28]), .cin(c[27]));
fulladder fa29 (.sum(sum[29]), .cout(c[29]), .a(a[29]), .b(b[29]), .cin(c[28]));
fulladder fa30 (.sum(sum[30]), .cout(c[30]), .a(a[30]), .b(b[30]), .cin(c[29]));
fulladder fa31 (.sum(sum[31]), .cout(cout),  .a(a[31]), .b(b[31]), .cin(c[30]));
endmodule

WEEK#1/Adder32Bit/tb_Adder32Bit.sv
`timescale 1ns/1ps

module tb_Adder32Bit();
reg [31:0] a, b;
reg cin;
wire [31:0] sum;
wire cout;

reg [31:0] expected_sum;
reg expected_cout;

integer i;
integer pass = 1;
integer fail = 0;

Adder32Bit dut(sum, cout, a, b, cin);

//GTKWave
initial begin
$dumpfile("Adder32Bit.vcd");
$dumpvars(0, tb_Adder32Bit);
end

task check;
begin
if ((sum === expected_sum) && (cout === expected_cout)) begin
$display("PASS: a=%0d b=%0d cin=%0b => sum=%0d cout=%0b", a, b, cin, sum, cout);
pass = pass + 1;
end else begin
$display("FAIL: a=%0d b=%0d cin=%0b => sum=%0d cout=%0b (expected sum=%0d cout=%0b)",
a, b, cin, sum, cout, expected_sum, expected_cout);
fail = fail + 1;
end
end
endtask

initial begin
$display("===== Adder32Bit Testbench Start =====");

a = 0; b = 0; cin = 0; #10;
expected_sum = a + b + cin;
expected_cout = 0;
check();

a = 1; b = 1; cin = 0; #10;
expected_sum = a + b + cin;
expected_cout = 0;
check();


a = 32'hFFFFFFFF; b = 1; cin = 0; #10;
{expected_cout, expected_sum} = a + b + cin;
check();

for (i = 0; i < 5; i = i + 1) begin
a = $urandom;
b = $urandom;
cin = $urandom % 2;
#10;
{expected_cout, expected_sum} = a + b + cin;
check();
end

a = 32'd15; b = 32'd2; cin = 0; #10;
expected_sum = a + b + 1;  
expected_cout = 0;
check();

a = 32'd7; b = 32'd3; cin = 1; #10;
expected_sum = 32'd0;       
expected_cout = 1;          
check();

//summary
$display("-----------Summary----------------");
$display("Total Passed: %0d", pass);
$display("Total Failed: %0d", fail);
$display("----------------------------------");

$finish;
end

endmodule

WEEK#1/Adder32Bit/Adder32Bit.vcd
$date
	Wed Dec 24 01:44:16 2025
$end
$version
	Icarus Verilog
$end
$timescale
	1ps
$end
$scope module tb_Adder32Bit $end
$var wire 32 ! sum [31:0] $end
$var wire 1 " cout $end
$var reg 32 # a [31:0] $end
$var reg 32 $ b [31:0] $end
$var reg 1 % cin $end
$var reg 1 & expected_cout $end
$var reg 32 ' expected_sum [31:0] $end
$var integer 32 ( fail [31:0] $end
$var integer 32 ) i [31:0] $end
$var integer 32 * pass [31:0] $end
$scope module dut $end
$var wire 32 + a [31:0] $end
$var wire 32 , b [31:0] $end
$var wire 1 % cin $end
$var wire 32 - sum [31:0] $end
$var wire 1 " cout $end
$var wire 31 . c [30:0] $end
$scope module fa0 $end
$var wire 1 / a $end
$var wire 1 0 b $end
$var wire 1 % cin $end
$var wire 1 1 cout $end
$var wire 1 2 sum $end
$upscope $end
$scope module fa1 $end
$var wire 1 3 a $end
$var wire 1 4 b $end
$var wire 1 5 cin $end
$var wire 1 6 cout $end
$var wire 1 7 sum $end
$upscope $end
$scope module fa10 $end
$var wire 1 8 a $end
$var wire 1 9 b $end
$var wire 1 : cin $end
$var wire 1 ; cout $end
$var wire 1 < sum $end
$upscope $end
$scope module fa11 $end
$var wire 1 = a $end
$var wire 1 > b $end
$var wire 1 ? cin $end
$var wire 1 @ cout $end
$var wire 1 A sum $end
$upscope $end
$scope module fa12 $end
$var wire 1 B a $end
$var wire 1 C b $end
$var wire 1 D cin $end
$var wire 1 E cout $end
$var wire 1 F sum $end
$upscope $end
$scope module fa13 $end
$var wire 1 G a $end
$var wire 1 H b $end
$var wire 1 I cin $end
$var wire 1 J cout $end
$var wire 1 K sum $end
$upscope $end
$scope module fa14 $end
$var wire 1 L a $end
$var wire 1 M b $end
$var wire 1 N cin $end
$var wire 1 O cout $end
$var wire 1 P sum $end
$upscope $end
$scope module fa15 $end
$var wire 1 Q a $end
$var wire 1 R b $end
$var wire 1 S cin $end
$var wire 1 T cout $end
$var wire 1 U sum $end
$upscope $end
$scope module fa16 $end
$var wire 1 V a $end
$var wire 1 W b $end
$var wire 1 X cin $end
$var wire 1 Y cout $end
$var wire 1 Z sum $end
$upscope $end
$scope module fa17 $end
$var wire 1 [ a $end
$var wire 1 \ b $end
$var wire 1 ] cin $end
$var wire 1 ^ cout $end
$var wire 1 _ sum $end
$upscope $end
$scope module fa18 $end
$var wire 1 ` a $end
$var wire 1 a b $end
$var wire 1 b cin $end
$var wire 1 c cout $end
$var wire 1 d sum $end
$upscope $end
$scope module fa19 $end
$var wire 1 e a $end
$var wire 1 f b $end
$var wire 1 g cin $end
$var wire 1 h cout $end
$var wire 1 i sum $end
$upscope $end
$scope module fa2 $end
$var wire 1 j a $end
$var wire 1 k b $end
$var wire 1 l cin $end
$var wire 1 m cout $end
$var wire 1 n sum $end
$upscope $end
$scope module fa20 $end
$var wire 1 o a $end
$var wire 1 p b $end
$var wire 1 q cin $end
$var wire 1 r cout $end
$var wire 1 s sum $end
$upscope $end
$scope module fa21 $end
$var wire 1 t a $end
$var wire 1 u b $end
$var wire 1 v cin $end
$var wire 1 w cout $end
$var wire 1 x sum $end
$upscope $end
$scope module fa22 $end
$var wire 1 y a $end
$var wire 1 z b $end
$var wire 1 { cin $end
$var wire 1 | cout $end
$var wire 1 } sum $end
$upscope $end
$scope module fa23 $end
$var wire 1 ~ a $end
$var wire 1 !" b $end
$var wire 1 "" cin $end
$var wire 1 #" cout $end
$var wire 1 $" sum $end
$upscope $end
$scope module fa24 $end
$var wire 1 %" a $end
$var wire 1 &" b $end
$var wire 1 '" cin $end
$var wire 1 (" cout $end
$var wire 1 )" sum $end
$upscope $end
$scope module fa25 $end
$var wire 1 *" a $end
$var wire 1 +" b $end
$var wire 1 ," cin $end
$var wire 1 -" cout $end
$var wire 1 ." sum $end
$upscope $end
$scope module fa26 $end
$var wire 1 /" a $end
$var wire 1 0" b $end
$var wire 1 1" cin $end
$var wire 1 2" cout $end
$var wire 1 3" sum $end
$upscope $end
$scope module fa27 $end
$var wire 1 4" a $end
$var wire 1 5" b $end
$var wire 1 6" cin $end
$var wire 1 7" cout $end
$var wire 1 8" sum $end
$upscope $end
$scope module fa28 $end
$var wire 1 9" a $end
$var wire 1 :" b $end
$var wire 1 ;" cin $end
$var wire 1 <" cout $end
$var wire 1 =" sum $end
$upscope $end
$scope module fa29 $end
$var wire 1 >" a $end
$var wire 1 ?" b $end
$var wire 1 @" cin $end
$var wire 1 A" cout $end
$var wire 1 B" sum $end
$upscope $end
$scope module fa3 $end
$var wire 1 C" a $end
$var wire 1 D" b $end
$var wire 1 E" cin $end
$var wire 1 F" cout $end
$var wire 1 G" sum $end
$upscope $end
$scope module fa30 $end
$var wire 1 H" a $end
$var wire 1 I" b $end
$var wire 1 J" cin $end
$var wire 1 K" cout $end
$var wire 1 L" sum $end
$upscope $end
$scope module fa31 $end
$var wire 1 M" a $end
$var wire 1 N" b $end
$var wire 1 O" cin $end
$var wire 1 " cout $end
$var wire 1 P" sum $end
$upscope $end
$scope module fa4 $end
$var wire 1 Q" a $end
$var wire 1 R" b $end
$var wire 1 S" cin $end
$var wire 1 T" cout $end
$var wire 1 U" sum $end
$upscope $end
$scope module fa5 $end
$var wire 1 V" a $end
$var wire 1 W" b $end
$var wire 1 X" cin $end
$var wire 1 Y" cout $end
$var wire 1 Z" sum $end
$upscope $end
$scope module fa6 $end
$var wire 1 [" a $end
$var wire 1 \" b $end
$var wire 1 ]" cin $end
$var wire 1 ^" cout $end
$var wire 1 _" sum $end
$upscope $end
$scope module fa7 $end
$var wire 1 `" a $end
$var wire 1 a" b $end
$var wire 1 b" cin $end
$var wire 1 c" cout $end
$var wire 1 d" sum $end
$upscope $end
$scope module fa8 $end
$var wire 1 e" a $end
$var wire 1 f" b $end
$var wire 1 g" cin $end
$var wire 1 h" cout $end
$var wire 1 i" sum $end
$upscope $end
$scope module fa9 $end
$var wire 1 j" a $end
$var wire 1 k" b $end
$var wire 1 l" cin $end
$var wire 1 m" cout $end
$var wire 1 n" sum $end
$upscope $end
$upscope $end
$scope task check $end
$upscope $end
$upscope $end
$enddefinitions $end
#0
$dumpvars
0n"
0m"
0l"
0k"
0j"
0i"
0h"
0g"
0f"
0e"
0d"
0c"
0b"
0a"
0`"
0_"
0^"
0]"
0\"
0["
0Z"
0Y"
0X"
0W"
0V"
0U"
0T"
0S"
0R"
0Q"
0P"
0O"
0N"
0M"
0L"
0K"
0J"
0I"
0H"
0G"
0F"
0E"
0D"
0C"
0B"
0A"
0@"
0?"
0>"
0="
0<"
0;"
0:"
09"
08"
07"
06"
05"
04"
03"
02"
01"
00"
0/"
0."
0-"
0,"
0+"
0*"
0)"
0("
0'"
0&"
0%"
0$"
0#"
0""
0!"
0~
0}
0|
0{
0z
0y
0x
0w
0v
0u
0t
0s
0r
0q
0p
0o
0n
0m
0l
0k
0j
0i
0h
0g
0f
0e
0d
0c
0b
0a
0`
0_
0^
0]
0\
0[
0Z
0Y
0X
0W
0V
0U
0T
0S
0R
0Q
0P
0O
0N
0M
0L
0K
0J
0I
0H
0G
0F
0E
0D
0C
0B
0A
0@
0?
0>
0=
0<
0;
0:
09
08
07
06
05
04
03
02
01
00
0/
b0 .
b0 -
b0 ,
b0 +
b1 *
bx )
b0 (
bx '
x&
0%
b0 $
b0 #
0"
b0 !
$end
#10000
b10 !
b10 -
17
15
b1 .
11
10
1/
b1 $
b1 ,
b1 #
b1 +
b10 *
0&
b0 '
#20000
1"
1O"
1K"
1J"
1A"
1@"
1<"
1;"
17"
16"
12"
11"
1-"
1,"
1("
1'"
1#"
1""
1|
1{
1w
1v
1r
1q
1h
1g
1c
1b
1^
1]
1Y
1X
1T
1S
1O
1N
1J
1I
1E
1D
1@
1?
1;
1:
1m"
1l"
1h"
1g"
1c"
1b"
1^"
1]"
1Y"
1X"
1T"
1S"
1F"
1E"
1m
1l
b1111111111111111111111111111111 .
16
07
0n
0G"
0U"
0Z"
0_"
0d"
0i"
0n"
0<
0A
0F
0K
0P
0U
0Z
0_
0d
0i
0s
0x
0}
0$"
0)"
0."
03"
08"
0="
0B"
0L"
b0 !
b0 -
0P"
13
1j
1C"
1Q"
1V"
1["
1`"
1e"
1j"
18
1=
1B
1G
1L
1Q
1V
1[
1`
1e
1o
1t
1y
1~
1%"
1*"
1/"
14"
19"
1>"
1H"
1M"
b11111111111111111111111111111111 #
b11111111111111111111111111111111 +
b11 *
b10 '
#30000
0v
0:
0r
0m"
1n"
1s
0l"
0q
0h"
0h
0"
1i
0E"
0]"
1i"
0g
01"
0@"
1P"
0m
0Y"
0g"
0c
0'"
0-"
0<"
0O"
0c"
0#"
0K"
1n
1Z"
1d"
1d
1$"
1."
1="
1L"
0l
0S"
0X"
0b"
0X
0b
0{
0""
0,"
06"
0;"
0J"
06
0F"
0T"
0^"
0T
0^
0w
0|
0("
02"
07"
b10111110000000001 .
0A"
0<
1F
0Z
17
0G"
0U"
0_"
1U
1_
0x
0}
0)"
03"
08"
0B"
b11010010100111101001001110100110 !
b11010010100111101001001110100110 -
02
1a"
1k"
19
1>
1C
1M
1W
1f
1!"
1I"
0/
03
0C"
0Q"
0["
0`"
0j"
0=
0L
0Q
0[
0e
0t
0y
0~
0%"
0/"
04"
0>"
0H"
1%
b1000000100010010101111010000001 $
b1000000100010010101111010000001 ,
b10010010000101010011010100100100 #
b10010010000101010011010100100100 +
b0 )
b100 *
1&
b0 '
#40000
18"
16"
12"
1U"
11"
1S"
1-"
1F"
0."
1F
1""
1,"
1D
1E"
1|
1("
1@
1m
0A
1x
0n
0_
1?
1v
1l
1:
0]
1{
1'"
1;
1r
16
1m"
0Y
1w
b111111100000111111000001111 .
1#"
0G"
0d"
0<
0s
03"
0L"
12
07
1_"
0n"
1P
1Z
0d
0}
1$"
0)"
b10111000101010011101000101110001 !
b10111000101010011101000101110001 -
1B"
1k
1D"
0a"
1f"
09
1H
1p
1u
1+"
10"
0I"
1N"
1/
13
0j
1["
0e"
1j"
0G
1L
0V
0`
1t
1y
1~
1%"
0*"
1>"
0M"
b10000110101110010111101100001101 $
b10000110101110010111101100001101 ,
b110001111100000101011001100011 #
b110001111100000101011001100011 +
b1 )
b101 *
0&
b11010010100111101001001110100110 '
#50000
01"
0-"
1."
0,"
0("
1)"
0'"
0#"
0d"
0L"
0b"
0J"
0""
0^"
0A"
0|
1_"
1B"
0?
0_
1}
0]"
0@"
0;
0]
1g
0{
0Y"
0I
0S
0<"
0Y
1c
0w
0E
0O
1<
1Z
1Z"
1="
0:
0X
1b
0v
0S"
0X"
0D
0N
06"
0;"
0m"
0T
1^
0r
02
1G"
0F"
1U"
0T"
0i"
0A
0@
0K
0J
0d
1i
1$"
03"
02"
18"
b1100000000000000111 .
07"
0P"
1n"
1F
1P
1U
1s
b111011111110011101011001111000 !
b111011111110011101011001111000 -
1x
00
14
0k
0D"
1R"
0f"
0>
0H
1\
1a
0f
0!"
1&"
0+"
00"
15"
0N"
03
1j
0j"
0B
0L
1Q
1[
0o
0t
0%"
1*"
b1001001101110101001000010010 $
b1001001101110101001000010010 ,
b110010110000101000010001100101 #
b110010110000101000010001100101 +
b10 )
b110 *
b10111000101010011101000101110001 '
#60000
1L"
1J"
1A"
0B"
1@"
1d"
1<"
1b"
0="
1^"
1;"
0_"
17"
1]"
08"
1Y"
16"
0Z"
12"
1X"
1T"
0U"
1_
1X
11"
1S"
1l"
1S
1]
1T
1-"
1F"
1h"
1O
b111110000001111100000101111111 .
1Y
1"
1n
1n"
1K
1U
0."
0G"
1A
0P
1Z
b1000001111110111011111010000100 !
b1000001111110111011111010000100 -
03"
1k
1W"
1\"
1f"
0k"
1H
1R
0a
0p
1+"
1:"
1?"
1N"
1C"
0V"
0["
1e"
1=
1L
1V
1`
1o
1/"
09"
0>"
1M"
b10111011001000111111000101110110 $
b10111011001000111111000101110110 ,
b10000110110101111100110100001101 #
b10000110110101111100110100001101 +
b11 )
b111 *
b111011111110011101011001111000 '
#70000
1'"
1#"
0$"
1""
1|
0d"
0L"
0b"
0}
0J"
0^"
1{
0A"
1w
1_"
0x
1B"
1P
0]"
1v
0@"
1N
0Y"
1r
0<"
1J
0K
0n
1Z"
1i"
1?
0s
1="
1P"
1I
0l
0X"
1g"
1:
1;
0b
1q
0;"
1O"
1E
17
06
1G"
1U"
0T"
1c"
1m"
1<
0^
0d
0i
1h
1)"
13"
18"
07"
b1000110111111011111011110001101 .
1K"
1A
0F
0U
b10111101000000100100111101111010 !
b10111101000000100100111101111010 -
0Z
04
1D"
0R"
0W"
0\"
1a"
1k"
19
0\
1a
1f
0&"
10"
05"
0:"
0?"
1I"
1V"
1["
1`"
1j"
0=
1B
0Q
0V
0[
19"
1>"
1H"
b11000110001011011111011110001100 $
b11000110001011011111011110001100 ,
b11110110110101000101011111101101 #
b11110110110101000101011111101101 +
b100 )
b1000 *
1&
b1000001111110111011111010000100 '
#80000
1U"
1S"
1F"
0i"
0)"
03"
0P"
07
1E"
0n"
0<
0A
0P
0_
08"
0g"
0I
0g
0v
0""
0'"
01"
0O"
05
1l
1m
0l"
0:
0?
0N
0S
0X
0]
0q
0{
06"
0c"
0E
0c
0r
0|
0#"
0-"
0K"
01
16
0n
0G"
0h"
0m"
0;
0K
0J
0O
0U
0T
0Z
0Y
0i
0h
0x
0w
b1110 .
02"
0"
0Z"
0_"
0s
0}
0$"
0="
0B"
b10001 !
b10001 -
12
14
0k
0D"
0a"
0f"
0k"
09
0C
0H
0M
0R
0W
0a
0f
0u
0+"
00"
0I"
0N"
13
0V"
0["
0`"
0e"
0j"
08
0B
0L
0`
0o
0y
0~
0*"
0/"
09"
0>"
0H"
0M"
0%
b10 $
b10 ,
b1111 #
b1111 +
b101 )
b1001 *
b10111101000000100100111101111010 '
#90000
0U"
0S"
17
0F"
15
1G"
b111 .
11
b1011 !
b1011 -
12
10
0C"
1%
b11 $
b11 ,
b111 #
b111 +
b1 (
0&
b10010 '
#100000
b10 (
1&
b0 '
