WEEK#1/Barrel_Shifter_32Bit/BarrelShifter.sv
module BarrelShifter(data_out, data_in, shift_amt, dir);
input [31:0] data_in;
input [4:0] shift_amt;
input dir;
output [31:0] data_out;

wire [31:0] w_data_in;
wire [4:0] w_shift_amt;
wire w_dir;
reg [31:0] r_data_out;

assign w_data_in = data_in;
assign w_shift_amt = shift_amt;
assign w_dir = dir;
assign data_out = r_data_out;

always @(*) begin
if (w_dir == 0)
r_data_out = w_data_in << w_shift_amt;
else
r_data_out = w_data_in >> w_shift_amt;
end
endmodule

WEEK#1/Barrel_Shifter_32Bit/BarrelShifter_tb.sv
`timescale 1ns/1ps

module BarrelShifter_tb;
reg  [31:0] data_in;
reg  [4:0]  shift_amt;
reg         dir;

wire [31:0] data_out;

reg [31:0] expected;
integer i;
integer pass = 1;
integer fail = 0;

BarrelShifter dut (.data_out(data_out), .data_in(data_in), .shift_amt(shift_amt), .dir(dir));

task check;
begin
if (data_out === expected) begin
$display("PASS: data_in=%0d shift=%0d dir=%b out=%0d", data_in, shift_amt, dir, data_out);
pass = pass + 1;
end
else begin
$display("FAIL: data_in=%0d shift=%0d dir=%b out=%0d expected=%0d", data_in, shift_amt, dir, data_out, expected);
fail = fail + 1;
end
end
endtask

initial begin
        // GTKWave dump
$dumpfile("BarrelShifter.vcd");
$dumpvars(0, BarrelShifter_tb);

$display("_____Test Start_____");

// Directed Tests
data_in = 32'd1; shift_amt = 5'd2; dir = 0; #10; expected = data_in << shift_amt; check();

data_in = 32'd1; shift_amt = 5'd2; dir = 1; #10; expected = data_in >> shift_amt; check();

data_in = 32'd2; shift_amt = 5'd5; dir = 0; # 10; expected = data_in << shift_amt; check();

data_in = 32'd2; shift_amt = 5'd5; dir = 1; #10; expected = data_in >> shift_amt; check();

// Random Tests
for (i = 0; i < 10; i = i + 1) begin
data_in = $random;
shift_amt = $random % 32;
dir = $random % 2;
#10;

if (dir == 0)
expected = data_in << shift_amt;
else
expected = data_in >> shift_amt;

check();
end

// Summary
$display("-------------SUMMARY--------------");
$display("Total Passed: %0d", pass);
$display("Total Failed: %0d", fail);
$display("---------------------------");

$finish;
end

endmodule

WEEK#1/Barrel_Shifter_32Bit/BarrelShifter.vcd
$date
	Tue Dec 23 10:07:10 2025
$end
$version
	Icarus Verilog
$end
$timescale
	1ps
$end
$scope module BarrelShifter_tb $end
$var wire 32 ! data_out [31:0] $end
$var reg 32 " data_in [31:0] $end
$var reg 1 # dir $end
$var reg 32 $ expected [31:0] $end
$var reg 5 % shift_amt [4:0] $end
$var integer 32 & fail [31:0] $end
$var integer 32 ' i [31:0] $end
$var integer 32 ( pass [31:0] $end
$scope module dut $end
$var wire 32 ) data_in [31:0] $end
$var wire 32 * data_out [31:0] $end
$var wire 1 # dir $end
$var wire 5 + shift_amt [4:0] $end
$var wire 32 , w_data_in [31:0] $end
$var wire 1 - w_dir $end
$var wire 5 . w_shift_amt [4:0] $end
$var reg 32 / r_data_out [31:0] $end
$upscope $end
$scope task check $end
$upscope $end
$upscope $end
$enddefinitions $end
#0
$dumpvars
b100 /
b10 .
0-
b1 ,
b10 +
b100 *
b1 )
b1 (
bx '
b0 &
b10 %
bx $
0#
b1 "
b100 !
$end
#10000
b0 !
b0 *
b0 /
1-
1#
b10 (
b100 $
#20000
b1000000 !
b1000000 *
b1000000 /
0-
0#
b101 .
b101 %
b101 +
b10 ,
b10 "
b10 )
b11 (
b0 $
#30000
b0 !
b0 *
b0 /
1-
1#
b100 (
b1000000 $
#40000
b1001000010101001101010010010 !
b1001000010101001101010010010 *
b1001000010101001101010010010 /
b1 .
b1 %
b1 +
b10010000101010011010100100100 ,
b10010000101010011010100100100 "
b10010000101010011010100100100 )
b0 '
b101 (
b0 $
#50000
b1011000111110000010 !
b1011000111110000010 *
b1011000111110000010 /
b1101 .
b1101 %
b1101 +
b10110001111100000101011001100011 ,
b10110001111100000101011001100011 "
b10110001111100000101011001100011 )
b1 '
b110 (
b1001000010101001101010010010 $
#60000
b10110010110000 !
b10110010110000 *
b10110010110000 /
b10010 .
b10010 %
b10010 +
b10110010110000101000010001100101 ,
b10110010110000101000010001100101 "
b10110010110000101000010001100101 )
b10 '
b111 (
b1011000111110000010 $
#70000
b11011 !
b11011 *
b11011 /
b10110 .
b10110 %
b10110 +
b110110101111100110100001101 ,
b110110101111100110100001101 "
b110110101111100110100001101 )
b11 '
b1000 (
b10110010110000 $
#80000
b1110110110101000101 !
b1110110110101000101 *
b1110110110101000101 /
b1100 .
b1100 %
b1100 +
b1110110110101000101011111101101 ,
b1110110110101000101011111101101 "
b1110110110101000101011111101101 )
b100 '
b1001 (
b11011 $
#90000
b1100110111001001001100011000000 !
b1100110111001001001100011000000 *
b1100110111001001001100011000000 /
0-
0#
b101 .
b101 %
b101 +
b11100011001101110010010011000110 ,
b11100011001101110010010011000110 "
b11100011001101110010010011000110 )
b101 '
b1010 (
b1110110110101000101 $
#100000
b11110010100000000000000000000000 !
b11110010100000000000000000000000 *
b11110010100000000000000000000000 /
b10111 .
b10111 %
b10111 +
b1110010101011111111011111100101 ,
b1110010101011111111011111100101 "
b1110010101011111111011111100101 )
b110 '
b1011 (
b1100110111001001001100011000000 $
#110000
b1101110001111000000000000000000 !
b1101110001111000000000000000000 *
b1101110001111000000000000000000 /
b10010 .
b10010 %
b10010 +
b1000111111011001101101110001111 ,
b1000111111011001101101110001111 "
b1000111111011001101101110001111 )
b111 '
b1100 (
b11110010100000000000000000000000 $
#120000
b10000000000011110101110100000000 !
b10000000000011110101110100000000 *
b10000000000011110101110100000000 /
b101 .
b101 %
b101 +
b11110100000000000111101011101000 ,
b11110100000000000111101011101000 "
b11110100000000000111101011101000 )
b1000 '
b1101 (
b1101110001111000000000000000000 $
#130000
b1101111010001110001 !
b1101111010001110001 *
b1101111010001110001 /
1-
1#
b1101 .
b1101 %
b1101 +
b11011110100011100010100010111101 ,
b11011110100011100010100010111101 "
b11011110100011100010100010111101 )
b1001 '
b1110 (
b10000000000011110101110100000000 $
#140000
b1010 '
b1111 (
b1101111010001110001 $
